ferreus_rbf-0.1.1.dist-info/METADATA
ferreus_rbf-0.1.1.dist-info/WHEEL
ferreus_rbf/__init__.py
ferreus_rbf/config/__init__.py
ferreus_rbf/config/__init__.pyi
ferreus_rbf/ferreus_rbf.pyd
ferreus_rbf/ferreus_rbf.pyi
ferreus_rbf/interpolant_config/__init__.py
ferreus_rbf/interpolant_config/__init__.pyi
ferreus_rbf/progress/__init__.py
ferreus_rbf/progress/__init__.pyi
ferreus_rbf/py.typed
ferreus_rbf-0.1.1.dist-info/RECORD
