Metadata-Version: 2.4
Name: ferreus_rbf
Version: 0.1.1
Classifier: Programming Language :: Rust
Classifier: Programming Language :: Python :: Implementation :: CPython
Classifier: Programming Language :: Python :: Implementation :: PyPy
Summary: Fast, memory efficient radial basis function (RBF) interpolation library
Keywords: rbf,radial-basis-function,isosurface,interpolation
Author-email: Daniel Owen <daniel.owen@live.com.au>
License-Expression: MIT
Requires-Python: >=3.8
Project-URL: Homepage, https://github.com/graphic-goose/ferreus_rbf_rs/
Project-URL: Documentation, https://graphic-goose.github.io/ferreus_rbf_rs/ferreus_rbf/
